README
setup.py
pypollution/__init__.py
pypollution.egg-info/PKG-INFO
pypollution.egg-info/SOURCES.txt
pypollution.egg-info/dependency_links.txt
pypollution.egg-info/top_level.txt
pypollution.egg-info/zip-safe