Metadata-Version: 1.0
Name: pypollution
Version: 1.1
Summary: A python library for making graph in real time (Hardware based Library).
Home-page: https://github.com/Krprashant94/pypollution
Author: Prashant Kumar
Author-email: kr.prashant94@gmail.com
License: MIT
Platform: UNKNOWN
